[
  {"numPessoa": "111" , "numProcesso": "444", "codigo": "1", "dataInicio": "24-02-2000"},
  {"numPessoa": "111" , "numProcesso": "333", "codigo": "1", "dataInicio": "23-01-2000"},
  {"numPessoa": "222" , "numProcesso": "222", "codigo": "2", "dataInicio": "22-12-2000"},
  {"numPessoa": "333" , "numProcesso": "111", "codigo": "3", "dataInicio": "11-11-2000"},
  {"numPessoa": "444" , "numProcesso": "111", "codigo": "4", "dataInicio": "11-11-2000"},
  {"numPessoa": "333" , "numProcesso": "111", "codigo": "3", "dataInicio": "11-11-2000"},
  {"numPessoa": "333" , "numProcesso": "111", "codigo": "3", "dataInicio": "11-11-2000"},
  {"numPessoa": "333" , "numProcesso": "111", "codigo": "3", "dataInicio": "11-11-2000"},
  {"numPessoa": "333" , "numProcesso": "111", "codigo": "3", "dataInicio": "11-11-2000"},
  {"numPessoa": "333" , "numProcesso": "111", "codigo": "3", "dataInicio": "11-11-2000"},
  {"numPessoa": "333" , "numProcesso": "111", "codigo": "3", "dataInicio": "11-11-2000"},
  {"numPessoa": "333" , "numProcesso": "111", "codigo": "3", "dataInicio": "11-11-2000"},
  {"numPessoa": "333" , "numProcesso": "111", "codigo": "3", "dataInicio": "11-11-2000"},
  {"numPessoa": "333" , "numProcesso": "111", "codigo": "3", "dataInicio": "11-11-2000"},
  {"numPessoa": "333" , "numProcesso": "111", "codigo": "3", "dataInicio": "11-11-2000"},
  {"numPessoa": "333" , "numProcesso": "111", "codigo": "3", "dataInicio": "11-11-2000"},
  {"numPessoa": "333" , "numProcesso": "111", "codigo": "3", "dataInicio": "11-11-2000"}

]
